<?xml version="1.0" encoding="UTF-8"?>
<jcr:root xmlns:sling="http://sling.apache.org/jcr/sling/1.0" xmlns:cq="http://www.day.com/jcr/cq/1.0" xmlns:jcr="http://www.jcp.org/jcr/1.0" xmlns:nt="http://www.jcp.org/jcr/nt/1.0"
          jcr:primaryType="nt:unstructured"
          sling:resourceType="cq/gui/components/authoring/dialog">
    <content
            jcr:primaryType="nt:unstructured"
            sling:resourceType="granite/ui/components/coral/foundation/fixedcolumns">
        <items jcr:primaryType="nt:unstructured">
            <column
                    jcr:primaryType="nt:unstructured"
                    sling:resourceType="granite/ui/components/coral/foundation/container">
                <items jcr:primaryType="nt:unstructured">

                    <text1
                            jcr:primaryType="nt:unstructured"
                            sling:resourceType="granite/ui/components/coral/foundation/form/textfield"
                            fieldLabel="Text 1"
                            name="./text1"/>
                    <text
                            jcr:primaryType="nt:unstructured"
                            sling:resourceType="granite/ui/components/coral/foundation/form/textfield"
                            fieldLabel="Text 2"
                            name="./text2"/>
                    <navItems
                            jcr:primaryType="nt:unstructured"
                            sling:resourceType="granite/ui/components/coral/foundation/form/multifield"
                            composite="{Boolean}true"
                            fieldLabel="Nav Items"
                            name="./navItem">
                        <field
                                jcr:primaryType="nt:unstructured"
                                sling:resourceType="granite/ui/components/coral/foundation/container"
                                 name="./actions">
                                <items jcr:primaryType="nt:unstructured">
                                <navTitle
                                        jcr:primaryType="nt:unstructured"
                                        sling:resourceType="granite/ui/components/coral/foundation/form/textfield"
                                        fieldLabel="Nav Title"
                                        name="./navTitle"/>
                                <navLink
                                        jcr:primaryType="nt:unstructured"
                                        sling:resourceType="granite/ui/components/coral/foundation/form/pathfield"
                                        fieldLabel="Nav Link"
                                        name="./navLink"/>

                            </items>
                        </field>
                    </navItems>
                </items>
            </column>
        </items>
    </content>
</jcr:root>